README.txt
setup.cfg
setup.py
docs/CREDITS.txt
docs/DESIGN.txt
docs/HISTORY.txt
docs/LICENSE.txt
iw/__init__.py
iw.sitestat.egg-info/PKG-INFO
iw.sitestat.egg-info/SOURCES.txt
iw.sitestat.egg-info/dependency_links.txt
iw.sitestat.egg-info/entry_points.txt
iw.sitestat.egg-info/namespace_packages.txt
iw.sitestat.egg-info/not-zip-safe
iw.sitestat.egg-info/requires.txt
iw.sitestat.egg-info/top_level.txt
iw/sitestat/__init__.py
iw/sitestat/config.py
iw/sitestat/configure.zcml
iw/sitestat/events.py
iw/sitestat/formlib.py
iw/sitestat/profiles.zcml
iw/sitestat/utils.py
iw/sitestat/version.txt
iw/sitestat/browser/__init__.py
iw/sitestat/browser/configure.zcml
iw/sitestat/browser/contentoptions.py
iw/sitestat/browser/controlpanel.py
iw/sitestat/browser/jsslot.py
iw/sitestat/browser/resources/sitestat.js
iw/sitestat/browser/resources/sitestat_icon.png
iw/sitestat/browser/templates/sitestatinline.js.dtml
iw/sitestat/interfaces/__init__.py
iw/sitestat/interfaces/layer.py
iw/sitestat/interfaces/linksfinder.py
iw/sitestat/linksfinders/__init__.py
iw/sitestat/linksfinders/standard.py
iw/sitestat/linksfinders/thirdparty/__init__.py
iw/sitestat/linksfinders/thirdparty/collage.py
iw/sitestat/linksfinders/thirdparty/plonearticle.py
iw/sitestat/linksfinders/thirdparty/simplealias.py
iw/sitestat/locales/README.txt
iw/sitestat/locales/iw.sitestat-manual.pot
iw/sitestat/locales/iw.sitestat.pot
iw/sitestat/locales/updatelocales.py
iw/sitestat/locales/fr/LC_MESSAGES/iw.sitestat.mo
iw/sitestat/locales/fr/LC_MESSAGES/iw.sitestat.po
iw/sitestat/profiles/default/actionicons.xml
iw/sitestat/profiles/default/actions.xml
iw/sitestat/profiles/default/browserlayer.xml
iw/sitestat/profiles/default/controlpanel.xml
iw/sitestat/profiles/default/iw.sitestat.txt
iw/sitestat/profiles/default/jsregistry.xml
iw/sitestat/profiles/default/metadata.xml
iw/sitestat/profiles/default/propertiestool.xml
iw/sitestat/profiles/default/viewlets.xml
iw/sitestat/tests/README.txt
iw/sitestat/tests/__init__.py
iw/sitestat/tests/base.py
iw/sitestat/tests/test_collage_linksfinder.txt
iw/sitestat/tests/test_doctests.py
iw/sitestat/tests/test_globalprocess.txt
iw/sitestat/tests/test_plonearticle_linksfinder.txt
iw/sitestat/tests/test_simplealias_linksfinder.txt
iw/sitestat/tests/test_standard_linksfinders.txt
