Metadata-Version: 1.0
Name: iw.sitestat
Version: 1.0.0-beta-1
Summary: Use sitestat to analyse your Plone site visits.
Home-page: http://plone.org/products/iw.sitestat
Author: Gilles Lenfant
Author-email: gilles.lenfant@ingeniweb.com
License: GPL
Keywords: plone sitestat
Platform: UNKNOWN
Classifier: Framework :: Plone
Classifier: Programming Language :: Python
Classifier: Topic :: Software Development :: Libraries :: Python Modules
